super_material/__init__.py
super_material/conductivity/MattisBardeenSuperconductorConductivity.py
super_material/conductivity/SuperconductorConductivityInterface.py
super_material/conductivity/ZimmermannSuperconductorConductivity.py
super_material/conductivity/__init__.py
super_material/constants.py
super_material/gap_energy/BCSGapEnergy.py
super_material/gap_energy/GapEnergyInterface.py
super_material/gap_energy/__init__.py
super_material/integrate/AbsoluteTolerance.py
super_material/integrate/BaseIntegrand.py
super_material/integrate/ChebyshevQuadratureTransform.py
super_material/integrate/ConjunctionTolerance.py
super_material/integrate/DisjunctionTolerance.py
super_material/integrate/FixedQuadratureInterface.py
super_material/integrate/GuassQuadratureIntervalTransform.py
super_material/integrate/IntegrandBoundary.py
super_material/integrate/IntegrandInterface.py
super_material/integrate/IntegrandInterval.py
super_material/integrate/IntegrandIntervalTransformInterface.py
super_material/integrate/IntegratorInterface.py
super_material/integrate/LinearIntegrandIntervalTransform.py
super_material/integrate/QuadpackIntegrator.py
super_material/integrate/RelativeTolerance.py
super_material/integrate/ScipyQuadratureIntegrator.py
super_material/integrate/ToleranceInterface.py
super_material/integrate/TransformedIntegrand.py
super_material/integrate/__init__.py
super_material-1.0.0a0.dist-info/LICENSE.md
super_material-1.0.0a0.dist-info/WHEEL
super_material-1.0.0a0.dist-info/METADATA
super_material-1.0.0a0.dist-info/RECORD
