Metadata-Version: 2.1
Name: super-material
Version: 1.0.0a0
Summary: Providing a constant interface to superconductor conductivity computations
Home-page: https://github.com/pleroux0/super_material
License: BSD-2-Clause
Author: Paul le Roux
Author-email: pleroux0@outlook.com
Requires-Python: >=3.8,<4.0
Classifier: License :: OSI Approved :: BSD License
Classifier: Programming Language :: Python :: 3
Classifier: Programming Language :: Python :: 3.8
Requires-Dist: numpy (>=1.19.1,<2.0.0)
Requires-Dist: scipy (>=1.5.2,<2.0.0)
Project-URL: Documentation, https://pleroux0.github.io/super_material/
Project-URL: Repository, https://github.com/pleroux0/super_material
